Workbook
Name Slicer_Department: #N/A
Name Slicer_Doctor_Name: #N/A
Name Slicer_Patient_Name: #N/A
Name Slicer_Ward: #N/A

Sheet Dashboard
D1: HOSPITAL MANAGEMENT DASHBOARD
A2: Metric | B2: Value
A3: Total Patients | B3: =COUNTA(Patients!A2:A51) -> 50
A4: Total Doctors | B4: =COUNTA(Doctors!A2:A11) -> 10
A5: Total Departments | B5: =COUNTA(Departments!A2:A6) -> 5
A6: Total Revenue | B6: =SUM(Billing!H2:H51) -> 46075
A7: Ward A Patients | B7: =COUNTIF(Admissions!C2:C51,"Ward A") -> 4
A8: Ward B Patients | B8: =COUNTIF(Admissions!C2:C51,"Ward B") -> 14
A9: Ward C Patients | B9: =COUNTIF(Admissions!C2:C51,"Ward C") -> 9
A10: Ward D Patients | B10: =COUNTIF(Admissions!C2:C51,"Ward D") -> 11
A11: Ward E Patients | B11: =COUNTIF(Admissions!C2:C51,"Ward E") -> 12

Sheet Patients
A1: Patient ID | B1: First Name | C1: Last Name | D1: Gender | E1: DOB | F1: Age | G1: Blood | H1: Phone | I1: State | J1: Insurance
A2: P001 | B2: James | C2: Smith | D2: Male | E2: 32874 | F2: 36 | G2: O+ | H2: 0800000000 | I2: California | J2: Yes
A3: P002 | B3: Mary | C3: Johnson | D3: Female | E3: 33239 | F3: 35 | G3: O+ | H3: 0800000001 | I3: Texas | J3: Yes
A4: P003 | B4: John | C4: Williams | D4: Male | E4: 33604 | F4: 34 | G4: O+ | H4: 0800000002 | I4: Florida | J4: Yes
A5: P004 | B5: Patricia | C5: Brown | D5: Female | E5: 33970 | F5: 33 | G5: O+ | H5: 0800000003 | I5: New York | J5: Yes
A6: P005 | B6: Robert | C6: Jones | D6: Male | E6: 34335 | F6: 32 | G6: O+ | H6: 0800000004 | I6: Illinois | J6: Yes
A7: P006 | B7: Jennifer | C7: Garcia | D7: Female | E7: 34700 | F7: 31 | G7: O+ | H7: 0800000005 | I7: Ohio | J7: Yes
A8: P007 | B8: Michael | C8: Miller | D8: Male | E8: 35065 | F8: 30 | G8: O+ | H8: 0800000006 | I8: Georgia | J8: Yes
A9: P008 | B9: Linda | C9: Davis | D9: Female | E9: 35431 | F9: 29 | G9: O+ | H9: 0800000007 | I9: Arizona | J9: Yes
A10: P009 | B10: William | C10: Rodriguez | D10: Male | E10: 35796 | F10: 28 | G10: O+ | H10: 0800000008 | I10: Washington | J10: Yes
A11: P010 | B11: Elizabeth | C11: Martinez | D11: Female | E11: 36161 | F11: 27 | G11: O+ | H11: 0800000009 | I11: Colorado | J11: Yes
A12: P011 | B12: David | C12: Smith | D12: Male | E12: 36526 | F12: 26 | G12: O+ | H12: 0800000010 | I12: California | J12: Yes
A13: P012 | B13: Susan | C13: Johnson | D13: Female | E13: 36892 | F13: 25 | G13: O+ | H13: 0800000011 | I13: Texas | J13: Yes
... A51: P050 | B51: Laura | C51: Martinez | D51: Female | E51: 36161 | F51: 27 | G51: O+ | H51: 0800000049 | I51: Colorado | J51: Yes

Sheet Sheet9

Sheet Doctors
A1: Doctor ID | B1: Doctor Name | C1: Department | D1: Specialty | E1: Qualification | F1: Phone | G1: Email | H1: Years
A2: DR001 | B2: Dr. Emily Carter | C2: Cardiology | D2: Specialist | E2: MBBS | F2: 0800000001 | G2: doc1@hosp.com | H2: 6
A3: DR002 | B3: Dr. Michael Brown | C3: Neurology | D3: Specialist | E3: MBBS | F3: 0800000002 | G3: doc2@hosp.com | H3: 7
A4: DR003 | B4: Dr. Sarah Johnson | C4: Pediatrics | D4: Specialist | E4: MBBS | F4: 0800000003 | G4: doc3@hosp.com | H4: 8
A5: DR004 | B5: Dr. David Wilson | C5: Orthopedics | D5: Specialist | E5: MBBS | F5: 0800000004 | G5: doc4@hosp.com | H5: 9
A6: DR005 | B6: Dr. Lisa Anderson | C6: Oncology | D6: Specialist | E6: MBBS | F6: 0800000005 | G6: doc5@hosp.com | H6: 10
A7: DR006 | B7: Dr. James Taylor | C7: Cardiology | D7: Specialist | E7: MBBS | F7: 0800000006 | G7: doc6@hosp.com | H7: 11
A8: DR007 | B8: Dr. Jennifer Moore | C8: Neurology | D8: Specialist | E8: MBBS | F8: 0800000007 | G8: doc7@hosp.com | H8: 12
A9: DR008 | B9: Dr. Robert Thomas | C9: Pediatrics | D9: Specialist | E9: MBBS | F9: 0800000008 | G9: doc8@hosp.com | H9: 13
A10: DR009 | B10: Dr. Karen White | C10: Orthopedics | D10: Specialist | E10: MBBS | F10: 0800000009 | G10: doc9@hosp.com | H10: 14
A11: DR010 | B11: Dr. Daniel Harris | C11: Oncology | D11: Specialist | E11: MBBS | F11: 0800000010 | G11: doc10@hosp.com | H11: 15

Sheet Sheet8

Sheet Departments
A1: Dept ID | B1: Department | C1: Floor | D1: Head | E1: Beds
A2: D01 | B2: Cardiology | C2: 1 | D2: Dr. Lisa Anderson | E2: 21
A3: D02 | B3: Neurology | C3: 2 | D3: Dr. James Taylor | E3: 22
A4: D03 | B4: Pediatrics | C4: 3 | D4: Dr. Jennifer Moore | E4: 23
A5: D04 | B5: Orthopedics | C5: 4 | D5: Dr. Robert Thomas | E5: 24
A6: D05 | B6: Oncology | C6: 5 | D6: Dr. Karen White | E6: 25

Sheet Sheet4
A3: Doctor Name | B3: Count of Appointment ID
A4: Dr. Daniel Harris | B4: 8
A5: Dr. David Wilson | B5: 8
A6: Dr. Emily Carter | B6: 3
A7: Dr. James Taylor | B7: 4
A8: Dr. Jennifer Moore | B8: 3
A9: Dr. Karen White | B9: 6
A10: Dr. Lisa Anderson | B10: 7
A11: Dr. Michael Brown | B11: 3
A12: Dr. Robert Thomas | B12: 3
A13: Dr. Sarah Johnson | B13: 5
A14: Grand Total | B14: 50

Sheet Appointments
A1: Appointment ID | B1: Patient Name | C1: Doctor Name | D1: Date | E1: Time | F1: Type | G1: Status
A2: A001 | B2: James | C2: Dr. Emily Carter | D2: 46204 | E2: 10:00 | F2: =Treatments!D2 -> Consultation | G2: Completed
A3: A002 | B3: Mary | C3: Dr. Michael Brown | D3: 46205 | E3: 10:00 | F3: =Treatments!D3 -> X-ray | G3: Completed
A4: A003 | B4: John | C4: Dr. Sarah Johnson | D4: 46206 | E4: 10:00 | F4: =Treatments!D4 -> Blood Test | G4: Completed
A5: A004 | B5: Patricia | C5: Dr. David Wilson | D5: 46207 | E5: 10:00 | F5: =Treatments!D5 -> Surgery | G5: Completed
A6: A005 | B6: Robert | C6: Dr. Lisa Anderson | D6: 46208 | E6: 10:00 | F6: =Treatments!D6 -> Physiotherapy | G6: Completed
A7: A006 | B7: Jennifer | C7: Dr. James Taylor | D7: 46209 | E7: 10:00 | F7: =Treatments!D7 -> Vaccination | G7: Completed
A8: A007 | B8: Michael | C8: Dr. Jennifer Moore | D8: 46210 | E8: 10:00 | F8: =Treatments!D8 -> MRI Scan | G8: Completed
A9: A008 | B9: Linda | C9: Dr. Robert Thomas | D9: 46211 | E9: 10:00 | F9: =Treatments!D9 -> CT Scan | G9: Completed
A10: A009 | B10: William | C10: Dr. Karen White | D10: 46212 | E10: 10:00 | F10: =Treatments!D10 -> Eye Exaimination | G10: Completed
A11: A010 | B11: Elizabeth | C11: Dr. Daniel Harris | D11: 46213 | E11: 10:00 | F11: =Treatments!D11 -> Postnatal Care | G11: Completed
A12: A011 | B12: David | C12: Dr. Emily Carter | D12: 46214 | E12: 10:00 | F12: =Treatments!D12 -> Emergency | G12: Completed
A13: A012 | B13: Susan | C13: Dr. Michael Brown | D13: 46215 | E13: 10:00 | F13: =Treatments!D13 -> Antenatal | G13: Completed
... A26: A025 | B26: Anthony | C26: Dr. Karen White | D26: 46228 | E26: 10:00 | F26: =Treatments!D26 -> Blood Test | G26: Completed
A27: A026 | B27: Sandra | C27: Dr. Daniel Harris | D27: 46229 | E27: 0.41666667 | F27: =Treatments!D27 -> Surgery | G27: Completed
A28: A027 | B28: Mark | C28: Dr. Daniel Harris | D28: 46230 | E28: 0.45833333 | F28: =Treatments!D28 -> Physiotherapy | G28: Completed
A29: A028 | B29: Ashley | C29: Dr. David Wilson | D29: 46231 | E29: 10:00 | F29: =Treatments!D29 -> Vaccination | G29: Completed
A30: A029 | B30: Donald | C30: Dr. Lisa Anderson | D30: 46204 | E30: 10:00 | F30: =Treatments!D30 -> General Check Up | G30: Completed
A31: A030 | B31: Kimberly | C31: Dr. Karen White | D31: 46205 | E31: 10:00 | F31: =Treatments!D31 -> CT Scan | G31: Completed
A32: A031 | B32: Steven | C32: Dr. Emily Carter | D32: 46206 | E32: 10:00 | F32: =Treatments!D32 -> Laboratory Test | G32: Completed
A33: A032 | B33: Emily | C33: Dr. Michael Brown | D33: 46207 | E33: 10:00 | F33: =Treatments!D33 -> Consultation | G33: Completed
A34: A033 | B34: Paul | C34: Dr. Sarah Johnson | D34: 46208 | E34: 10:00 | F34: =Treatments!D34 -> Dental Check Up | G34: Completed
A35: A034 | B35: Donna | C35: Dr. David Wilson | D35: 46209 | E35: 10:00 | F35: =Treatments!D35 -> Blood Test | G35: Completed
A36: A035 | B36: Andrew | C36: Dr. Lisa Anderson | D36: 46210 | E36: 10:00 | F36: =Treatments!D36 -> Surgery | G36: Completed
A37: A036 | B37: Michelle | C37: Dr. James Taylor | D37: 46211 | E37: 10:00 | F37: =Treatments!D37 -> Physiotherapy | G37: Completed
A38: A037 | B38: Joshua | C38: Dr. Jennifer Moore | D38: 46212 | E38: 10:00 | F38: =Treatments!D38 -> Vaccination | G38: Completed
A39: A038 | B39: Carol | C39: Dr. Robert Thomas | D39: 46213 | E39: 10:00 | F39: =Treatments!D39 -> MRI Scan | G39: Completed
A40: A039 | B40: Kenneth | C40: Dr. Karen White | D40: 46214 | E40: 10:00 | F40: =Treatments!D40 -> CT Scan | G40: Completed
... A51: A050 | B51: Laura | C51: Dr. Lisa Anderson | D51: 46225 | E51: 10:00 | F51: =Treatments!D51 -> Dental Check Up | G51: Completed

Sheet Sheet10

Sheet Admissions
A1: Admission ID | B1: Patient Name | C1: Ward | D1: Bed | E1: Admission | F1: Discharge | G1: Length | H1: Diagnosis
A2: AD001 | B2: James | C2: Ward A | D2: 1 | E2: 46204 | F2: 46207 | G2: =F2-E2 -> 3 | H2: Diagnosis
A3: AD002 | B3: Mary | C3: Ward A | D3: 2 | E3: 46205 | F3: 46208 | G3: =F3-E3 -> 3 | H3: Diagnosis
A4: AD003 | B4: John | C4: Ward A | D4: 3 | E4: 46206 | F4: 46209 | G4: =F4-E4 -> 3 | H4: Diagnosis
A5: AD004 | B5: Patricia | C5: Ward A | D5: 4 | E5: 46207 | F5: 46210 | G5: =F5-E5 -> 3 | H5: Diagnosis
A6: AD005 | B6: Robert | C6: Ward B | D6: 5 | E6: 46208 | F6: 46211 | G6: =F6-E6 -> 3 | H6: Diagnosis
A7: AD006 | B7: Jennifer | C7: Ward B | D7: 6 | E7: 46209 | F7: 46212 | G7: =F7-E7 -> 3 | H7: Diagnosis
A8: AD007 | B8: Michael | C8: Ward B | D8: 7 | E8: 46210 | F8: 46213 | G8: =F8-E8 -> 3 | H8: Diagnosis
A9: AD008 | B9: Linda | C9: Ward B | D9: 8 | E9: 46211 | F9: 46214 | G9: =F9-E9 -> 3 | H9: Diagnosis
A10: AD009 | B10: William | C10: Ward B | D10: 9 | E10: 46212 | F10: 46215 | G10: =F10-E10 -> 3 | H10: Diagnosis
A11: AD010 | B11: Elizabeth | C11: Ward B | D11: 10 | E11: 46213 | F11: 46216 | G11: =F11-E11 -> 3 | H11: Diagnosis
A12: AD011 | B12: David | C12: Ward B | D12: 11 | E12: 46214 | F12: 46217 | G12: =F12-E12 -> 3 | H12: Diagnosis
A13: AD012 | B13: Susan | C13: Ward B | D13: 12 | E13: 46215 | F13: 46218 | G13: =F13-E13 -> 3 | H13: Diagnosis
... A51: AD050 | B51: Laura | C51: Ward E | D51: 50 | E51: 46225 | F51: 46228 | G51: =F51-E51 -> 3 | H51: Diagnosis

Sheet Sheet7
A3: Treatment | B3: Sum of Cost
A4: Antenatal | B4: 600
A5: Blood Test | B5: 2090
A6: Consultation | B6: 1119
A7: CT Scan | B7: 3210
A8: Dental Check Up | B8: 1120
A9: Emergency | B9: 700
A10: Eye Exaimination | B10: 200
A11: General Check Up | B11: 1000
A12: Laboratory Test | B12: 431
A13: MRI Scan | B13: 2400
A14: Physiotherapy | B14: 2227
A15: Postnatal Care | B15: 200
... A20: Grand Total | B20: 30275

Sheet Treatments
A1: Treatment ID | B1: Patient Name | C1: Doctor Name | D1: Treatment | E1: Date | F1: Cost
A2: T001 | B2: James | C2: Dr. Emily Carter | D2: Consultation | E2: 46204 | F2: 200
A3: T002 | B3: Mary | C3: Dr. Michael Brown | D3: X-ray | E3: 46205 | F3: 500
A4: T003 | B4: John | C4: Dr. Sarah Johnson | D4: Blood Test | E4: 46206 | F4: 600
A5: T004 | B5: Patricia | C5: Dr. David Wilson | D5: Surgery | E5: 46207 | F5: 1000
A6: T005 | B6: Robert | C6: Dr. Lisa Anderson | D6: Physiotherapy | E6: 46208 | F6: 400
A7: T006 | B7: Jennifer | C7: Dr. James Taylor | D7: Vaccination | E7: 46209 | F7: 300
A8: T007 | B8: Michael | C8: Dr. Jennifer Moore | D8: MRI Scan | E8: 46210 | F8: 800
A9: T008 | B9: Linda | C9: Dr. Robert Thomas | D9: CT Scan | E9: 46211 | F9: 900
A10: T009 | B10: William | C10: Dr. Karen White | D10: Eye Exaimination | E10: 46212 | F10: 200
A11: T010 | B11: Elizabeth | C11: Dr. Daniel Harris | D11: Postnatal Care | E11: 46213 | F11: 200
A12: T011 | B12: David | C12: Dr. Emily Carter | D12: Emergency | E12: 46214 | F12: 700
A13: T012 | B13: Susan | C13: Dr. Michael Brown | D13: Antenatal | E13: 46215 | F13: 600
... A51: T050 | B51: Laura | C51: Dr. Lisa Anderson | D51: Dental Check Up | E51: 46225 | F51: 620

Sheet Pharmacy
A1: Medicine ID | B1: Medicine | C1: Category | D1: Unit Price | E1: Qty | F1: Supplier | G1: Expiry
A2: M001 | B2: Medicine1 | C2: General | D2: 11 | E2: 99 | F2: Supplier | G2: 46752
A3: M002 | B3: Medicine2 | C3: General | D3: 12 | E3: 98 | F3: Supplier | G3: 46752
A4: M003 | B4: Medicine3 | C4: General | D4: 13 | E4: 97 | F4: Supplier | G4: 46752
A5: M004 | B5: Medicine4 | C5: General | D5: 14 | E5: 96 | F5: Supplier | G5: 46752
A6: M005 | B6: Medicine5 | C6: General | D6: 15 | E6: 95 | F6: Supplier | G6: 46752
A7: M006 | B7: Medicine6 | C7: General | D7: 16 | E7: 94 | F7: Supplier | G7: 46752
A8: M007 | B8: Medicine7 | C8: General | D8: 17 | E8: 93 | F8: Supplier | G8: 46752
A9: M008 | B9: Medicine8 | C9: General | D9: 18 | E9: 92 | F9: Supplier | G9: 46752
A10: M009 | B10: Medicine9 | C10: General | D10: 19 | E10: 91 | F10: Supplier | G10: 46752
A11: M010 | B11: Medicine10 | C11: General | D11: 20 | E11: 90 | F11: Supplier | G11: 46752

Sheet Prescriptions
A1: Prescription ID | B1: Patient Name | C1: Doctor Name | D1: Medicine ID | E1: Qty | F1: Date
A2: PR001 | B2: James | C2: Dr. Emily Carter | D2: M001 | E2: 2 | F2: 46204
A3: PR002 | B3: Mary | C3: Dr. Michael Brown | D3: M001 | E3: 2 | F3: 46205
A4: PR003 | B4: John | C4: Dr. Sarah Johnson | D4: M001 | E4: 2 | F4: 46206
A5: PR004 | B5: Patricia | C5: Dr. David Wilson | D5: M001 | E5: 2 | F5: 46207
A6: PR005 | B6: Robert | C6: Dr. Lisa Anderson | D6: M001 | E6: 2 | F6: 46208
A7: PR006 | B7: Jennifer | C7: Dr. James Taylor | D7: M001 | E7: 2 | F7: 46209
A8: PR007 | B8: Michael | C8: Dr. Jennifer Moore | D8: M001 | E8: 2 | F8: 46210
A9: PR008 | B9: Linda | C9: Dr. Robert Thomas | D9: M001 | E9: 2 | F9: 46211
A10: PR009 | B10: William | C10: Dr. Karen White | D10: M001 | E10: 2 | F10: 46212
A11: PR010 | B11: Elizabeth | C11: Dr. Daniel Harris | D11: M001 | E11: 2 | F11: 46213
A12: PR011 | B12: David | C12: Dr. Emily Carter | D12: M001 | E12: 2 | F12: 46214
A13: PR012 | B13: Susan | C13: Dr. Michael Brown | D13: M001 | E13: 2 | F13: 46215
... A51: PR050 | B51: Laura | C51: Dr. Lisa Anderson | D51: M001 | E51: 2 | F51: 46225

Sheet Billing
A1: Invoice ID | B1: Patient Name | C1: Consultation | D1: Treatment | E1: Medicine | F1: Room | G1: Other | H1: Total | I1: Paid | J1: Balance | K1: Status
A2: INV001 | B2: James | C2: 50 | D2: 500 | E2: 30 | F2: 200 | G2: 20 | H2: =SUM(C2:G2) -> 800 | I2: 300 | J2: =H2-I2 -> 500 | K2: Paid
A3: INV002 | B3: Mary | C3: 50 | D3: 500 | E3: 30 | F3: 200 | G3: 20 | H3: =SUM(C3:G3) -> 800 | I3: 300 | J3: =H3-I3 -> 500 | K3: Paid
A4: INV003 | B4: John | C4: 50 | D4: 600 | E4: 30 | F4: 200 | G4: 20 | H4: =SUM(C4:G4) -> 900 | I4: 300 | J4: =H4-I4 -> 600 | K4: Paid
A5: INV004 | B5: Patricia | C5: 50 | D5: 1000 | E5: 30 | F5: 200 | G5: 20 | H5: =SUM(C5:G5) -> 1300 | I5: 300 | J5: =H5-I5 -> 1000 | K5: Paid
A6: INV005 | B6: Robert | C6: 50 | D6: 400 | E6: 30 | F6: 200 | G6: 20 | H6: =SUM(C6:G6) -> 700 | I6: 300 | J6: =H6-I6 -> 400 | K6: Paid
A7: INV006 | B7: Jennifer | C7: 50 | D7: 300 | E7: 30 | F7: 200 | G7: 20 | H7: =SUM(C7:G7) -> 600 | I7: 300 | J7: =H7-I7 -> 300 | K7: Paid
A8: INV007 | B8: Michael | C8: 50 | D8: 800 | E8: 30 | F8: 200 | G8: 20 | H8: =SUM(C8:G8) -> 1100 | I8: 300 | J8: =H8-I8 -> 800 | K8: Paid
A9: INV008 | B9: Linda | C9: 50 | D9: 900 | E9: 30 | F9: 200 | G9: 20 | H9: =SUM(C9:G9) -> 1200 | I9: 300 | J9: =H9-I9 -> 900 | K9: Paid
A10: INV009 | B10: William | C10: 50 | D10: 200 | E10: 30 | F10: 200 | G10: 20 | H10: =SUM(C10:G10) -> 500 | I10: 300 | J10: =H10-I10 -> 200 | K10: Paid
A11: INV010 | B11: Elizabeth | C11: 50 | D11: 200 | E11: 30 | F11: 200 | G11: 20 | H11: =SUM(C11:G11) -> 500 | I11: 300 | J11: =H11-I11 -> 200 | K11: Paid
A12: INV011 | B12: David | C12: 50 | D12: 700 | E12: 30 | F12: 200 | G12: 20 | H12: =SUM(C12:G12) -> 1000 | I12: 300 | J12: =H12-I12 -> 700 | K12: Paid
A13: INV012 | B13: Susan | C13: 50 | D13: 600 | E13: 30 | F13: 200 | G13: 20 | H13: =SUM(C13:G13) -> 900 | I13: 300 | J13: =H13-I13 -> 600 | K13: Paid
... A51: INV050 | B51: Laura | C51: 50 | D51: 620 | E51: 50 | F51: 200 | G51: 20 | H51: =SUM(C51:G51) -> 940 | I51: 300 | J51: =H51-I51 -> 640 | K51: Paid

Sheet Summary 
A1: Metric | B1: Value | F1: Metric | G1: Value
A2: Total Patients | B2: =COUNTA(Patients!A2:A51) -> 50 | F2: Ward A Patients | G2: =COUNTIF(Admissions!C2:C51,"Ward A") -> 4
A3: Total Doctors | B3: =COUNTA(Doctors!A2:A11) -> 10 | F3: Ward B Patients | G3: =COUNTIF(Admissions!C2:C51,"Ward B") -> 14
A4: Total Departments | B4: =COUNTA(Departments!A2:A6) -> 5 | F4: Ward C Patients | G4: =COUNTIF(Admissions!C2:C51,"Ward C") -> 9
A5: Total Revenue | B5: =SUM(Billing!H2:H51) -> 46075 | F5: Ward D Patients | G5: =COUNTIF(Admissions!C2:C51,"Ward D") -> 11
A6: Highest Bill | B6: =MAX(Billing!H2:H51) -> 2310 | F6: Ward E Patients | G6: =COUNTIF(Admissions!C2:C51,"Ward E") -> 12
A7: Lowest Bill | B7: =MIN(Billing!H2:H51) -> 500 | F7: Numbers of Bed | G7: =COUNTA(Admissions!D2:D51) -> 50
A8: Average Bill | B8: =AVERAGE(Billing!H2:H51) -> 921.5 | F8: Quantity of Drugs | G8: =SUM(Pharmacy!E2:E11) -> 945
