Workbook

Sheet Sheet2
A3: Shop Location | B3: Sum of Net Amount
A4: East Midlands | B4: 31864.35
A5: East of England | B5: 98086.8
A6: London | B6: 226519.65
A7: West Midlands | B7: 1179894.4
A8: Grand Total | B8: 1536365.2

Sheet Sheet3
A3: Payment | B3: Sum of Total Sales
A4: Cash | B4: 1182654
A5: POS | B5: 186379
A6: Transfer | B6: 94172
A7: Grand Total | B7: 1463205

Sheet Sheet5
A3: Category | B3: Sum of Total Sales
A4: Bakery | B4: 11748
A5: Beverage | B5: 9446
A6: Dairy | B6: 77671
A7: Food | B7: 1139765
A8: Grocery | B8: 99591
A9: Household | B9: 78641
A10: Snacks | B10: 46343
A11: Grand Total | B11: 1463205

Sheet Dashboard

Sheet ss
A1: Aldi Uk Supermarket Sales Record
A2: Date | B2: Customer Name | C2: Shop Location | D2: Product | E2: Category | F2: Qty | G2: Unit Price | H2: Discount | I2: Total Sales | J2: VAT | K2: Net Amount | L2: Payment
A3: 01/07/2026 | B3: John | C3: London | D3: Rice | E3: Food | F3: 2 | G3: 45000 | H3: 1000 | I3: =F3*G3-H3 -> 89000 | J3: =I3*5% -> 4450 | K3: =I3+J3 -> 93450 | L3: Cash
A4: 01/07/2026 | B4: Mary | C4: East Midlands | D4: Milk | E4: Dairy | F4: 3 | G4: 3500 | H4: 500 | I4: =F4*G4-H4 -> 10000 | J4: =I4*5% -> 500 | K4: =I4+J4 -> 10500 | L4: POS
A5: 02/07/2026 | B5: David | C5: West Midlands | D5: Bread | E5: Bakery | F5: 7 | G5: 1500 | H5: 200 | I5: =F5*G5-H5 -> 10300 | J5: =I5*5% -> 515 | K5: =I5+J5 -> 10815 | L5: Transfer
A6: 02/07/2026 | B6: Grace | C6: East of England | D6: Sugar | E6: Grocery | F6: 4 | G6: 2500 | H6: 300 | I6: =F6*G6-H6 -> 9700 | J6: =I6*5% -> 485 | K6: =I6+J6 -> 10185 | L6: Cash
A7: 03/07/2026 | B7: Peter | C7: London | D7: Soft Drink | E7: Beverage | F7: 6 | G7: 800 | H7: 100 | I7: =F7*G7-H7 -> 4700 | J7: =I7*5% -> 235 | K7: =I7+J7 -> 4935 | L7: POS
A8: 03/07/2026 | B8: Sarah | C8: East Midlands | D8: Indomie | E8: Food | F8: 12 | G8: 700 | H8: 500 | I8: =F8*G8-H8 -> 7900 | J8: =I8*5% -> 395 | K8: =I8+J8 -> 8295 | L8: Cash
A9: 04/07/2026 | B9: James | C9: West Midlands | D9: Cooking Oil | E9: Grocery | F9: 2 | G9: 19500 | H9: 500 | I9: =F9*G9-H9 -> 38500 | J9: =I9*5% -> 1925 | K9: =I9+J9 -> 40425 | L9: Transfer
A10: 04/07/2026 | B10: Esther | C10: East of England | D10: Biscuit | E10: Snacks | F10: 8 | G10: 1500 | H10: 100 | I10: =F10*G10-H10 -> 11900 | J10: =I10*5% -> 595 | K10: =I10+J10 -> 12495 | L10: POS
A11: 05/07/2026 | B11: Michael | C11: East of England | D11: Eggs | E11: Dairy | F11: 3 | G11: 3000 | H11: 200 | I11: =F11*G11-H11 -> 8800 | J11: =I11*5% -> 440 | K11: =I11+J11 -> 9240 | L11: Cash
A12: 05/07/2026 | B12: Blessing | C12: London | D12: Soap | E12: Household | F12: 10 | G12: 1200 | H12: 500 | I12: =F12*G12-H12 -> 11500 | J12: =I12*5% -> 575 | K12: =I12+J12 -> 12075 | L12: POS
A13: 46149 | B13: Ben | C13: West Midlands | D13: Rice | E13: Food | F13: 23 | G13: 45000 | H13: 50 | I13: =F13*G13-H13 -> 1034950 | J13: =I13*5% -> 51747.5 | K13: =I13+J13 -> 1086697.5 | L13: Cash
A14: 46149 | B14: Mary A. | C14: East of England | D14: Milk | E14: Dairy | F14: 12 | G14: 3500 | H14: 51 | I14: =F14*G14-H14 -> 41949 | J14: =I14*5% -> 2097.45 | K14: =I14+J14 -> 44046.45 | L14: POS
A15: 46149 | B15: Smith | C15: London | D15: Bread | E15: Bakery | F15: 3 | G15: 1500 | H15: 52 | I15: =F15*G15-H15 -> 4448 | J15: =I15*5% -> 222.4 | K15: =I15+J15 -> 4670.4 | L15: Transfer
A16: 05/07/2026 | B16: Berry | C16: East Midlands | D16: Sugar | E16: Grocery | F16: 5 | G16: 2500 | H16: 53 | I16: =F16*G16-H16 -> 12447 | J16: =I16*5% -> 622.35 | K16: =I16+J16 -> 13069.35 | L16: Cash
A17: 05/07/2026 | B17: Vicky | C17: West Midlands | D17: Soft Drink | E17: Beverage | F17: 6 | G17: 800 | H17: 54 | I17: =F17*G17-H17 -> 4746 | J17: =I17*5% -> 237.3 | K17: =I17+J17 -> 4983.3 | L17: POS
A18: 46149 | B18: Tom | C18: East of England | D18: Indomie | E18: Food | F18: 6 | G18: 700 | H18: 55 | I18: =F18*G18-H18 -> 4145 | J18: =I18*5% -> 207.25 | K18: =I18+J18 -> 4352.25 | L18: Cash
A19: 46149 | B19: Toni | C19: London | D19: Cooking Oil | E19: Grocery | F19: 2 | G19: 19500 | H19: 56 | I19: =F19*G19-H19 -> 38944 | J19: =I19*5% -> 1947.2 | K19: =I19+J19 -> 40891.2 | L19: Transfer
A20: 46149 | B20: Samson | C20: West Midlands | D20: Biscuit | E20: Snacks | F20: 23 | G20: 1500 | H20: 57 | I20: =F20*G20-H20 -> 34443 | J20: =I20*5% -> 1722.15 | K20: =I20+J20 -> 36165.15 | L20: POS
A21: 15/7/2026 | B21: Chico | C21: East of England | D21: Eggs | E21: Dairy | F21: 4 | G21: 3000 | H21: 58 | I21: =F21*G21-H21 -> 11942 | J21: =I21*5% -> 597.1 | K21: =I21+J21 -> 12539.1 | L21: Cash
A22: 15/7/2026 | B22: Kather | C22: London | D22: Soap | E22: Household | F22: 56 | G22: 1200 | H22: 59 | I22: =F22*G22-H22 -> 67141 | J22: =I22*5% -> 3357.05 | K22: =I22+J22 -> 70498.05 | L22: POS
A23: 15/7/2026 | B23: Paul | C23: West Midlands | D23: Rice | E23: Food | F23: 20 | G23: 190 | H23: 30 | I23: =F23*G23-H23 -> 3770 | J23: =I23*5% -> 188.5 | K23: =I23+J23 -> 3958.5 | L23: Cash
A24: 20/7/2026 | B24: Sarah O. | C24: East of England | D24: Milk | E24: Dairy | F24: 10 | G24: 500 | H24: 20 | I24: =F24*G24-H24 -> 4980 | J24: =I24*5% -> 249 | K24: =I24+J24 -> 5229 | L24: Transfer

Sheet Sales Summary
A1: Sale Summary | B1: Value
A2: Total Sales | B2: =SUM(ss!I3:I24) -> 1466205
A3: Total Net Amount | B3: =SUM(ss!K3:K24) -> 1539515.2
A4: Total Quantity | B4: =SUM(ss!F3:F24) -> 227
A5: Average Sale | B5: =AVERAGE(ss!K3:K24) -> 69977.966
A6: Highest Sale | B6: =MAX(ss!K3:K24) -> 1086697.5
A7: Lowest Sale | B7: =MIN(ss!K3:K24) -> 3958.5
A8: East Midlands | B8: =SUMIF(ss!C3:C24,A8,ss!K3:K24) -> 31864.35
A9: West Midlands | B9: =SUMIF(ss!C4:C25,A9,ss!K4:K25) -> 1183044.4
A10: East of England | B10: =SUMIF(ss!C5:C26,A10,ss!K5:K26) -> 98086.8
A11: London | B11: =SUMIF(ss!C6:C27,A11,ss!K6:K27) -> 133069.65
